{
	"commentStamp" : "JulienDelplanque 8/14/2016 12:31",
	"super" : "PSQLTokenizer",
	"category" : "PostgreSQL-Experiments",
	"classinstvars" : [ ],
	"pools" : [ ],
	"classvars" : [ ],
	"instvars" : [
		"expression",
		"columnReference",
		"correlation",
		"columnName",
		"primary",
		"functionParameterName",
		"orderByClause",
		"selectCommand",
		"withQuery",
		"fromClause",
		"whereClause",
		"groupByClause",
		"havingClause",
		"windowClause",
		"unionIntersectExceptClause",
		"limitClause",
		"offsetClause",
		"fetchClause",
		"forClause",
		"insertCommand",
		"updateCommand",
		"deleteCommand",
		"withClause",
		"from",
		"as",
		"only",
		"select",
		"all",
		"distinct",
		"on",
		"with",
		"recursive",
		"order",
		"by",
		"asc",
		"desc",
		"nulls",
		"first",
		"last",
		"fromItems1",
		"fromItems2",
		"fromItems3",
		"tableName",
		"alias",
		"columnAlias",
		"queryName",
		"functionName",
		"aggregateName",
		"fromItems4",
		"fromItems5",
		"fromItems",
		"fromItems6",
		"natural",
		"joinType",
		"using",
		"inner",
		"join",
		"left",
		"outer",
		"right",
		"full",
		"cross",
		"keyword",
		"identifier",
		"where"
	],
	"name" : "PSQLGrammar",
	"type" : "normal"
}